ckanext/__init__.py
ckanext/query_dois/__init__.py
ckanext/query_dois/cli.py
ckanext/query_dois/helpers.py
ckanext/query_dois/model.py
ckanext/query_dois/plugin.py
ckanext/query_dois/lib/__init__.py
ckanext/query_dois/lib/doi.py
ckanext/query_dois/lib/emails.py
ckanext/query_dois/lib/query.py
ckanext/query_dois/lib/stats.py
ckanext/query_dois/lib/utils.py
ckanext/query_dois/logic/__init__.py
ckanext/query_dois/logic/action.py
ckanext/query_dois/logic/auth.py
ckanext/query_dois/logic/schema.py
ckanext/query_dois/migration/query_dois/README
ckanext/query_dois/migration/query_dois/alembic.ini
ckanext/query_dois/migration/query_dois/env.py
ckanext/query_dois/migration/query_dois/script.py.mako
ckanext/query_dois/migration/query_dois/versions/a74242a670e0_set_old_query_version.py
ckanext/query_dois/routes/__init__.py
ckanext/query_dois/routes/_helpers.py
ckanext/query_dois/routes/query_doi.py
ckanext/query_dois/theme/assets/webassets.yml
ckanext/query_dois/theme/assets/less/query_dois.less
ckanext/query_dois/theme/assets/less/visual_query.less
ckanext/query_dois/theme/assets/scripts/multisearch_download.js
ckanext/query_dois/theme/templates/query_dois/multisearch_landing_page.html
ckanext/query_dois/theme/templates/query_dois/single_landing_page.html
ckanext/query_dois/theme/templates/query_dois/snippets/recent_dois_sidebar.html
ckanext/query_dois/theme/templates/query_dois/snippets/visual_datastore_multisearch.html
ckanext/query_dois/theme/templates/query_dois/snippets/visual_datastore_search.html
ckanext_query_dois-6.0.3.dist-info/licenses/LICENSE
docs/_scripts/gen_api_pages.py
tests/unit/__init__.py
tests/unit/conftest.py
tests/unit/test_helpers.py
tests/unit/test_plugin.py
tests/unit/test_utils.py
ckanext_query_dois-6.0.3.dist-info/METADATA
ckanext_query_dois-6.0.3.dist-info/WHEEL
ckanext_query_dois-6.0.3.dist-info/entry_points.txt
ckanext_query_dois-6.0.3.dist-info/top_level.txt
ckanext_query_dois-6.0.3.dist-info/RECORD
